{"interface":"none","output":"14.pcap","outputdir":"/home/zhangzq/桌面/程序/ssl_ml/data/json/json-web/facebook.com","info":"none","count":0,"bidir":1,"num_pkts":0,"dist":1,"tls":1,"bpf":"none"}
{"sa":"10.144.94.253","da":"31.13.95.36","pr":6,"sp":64042,"dp":443,"ob":326,"op":8,"ib":3828,"ip":7,"ts":1500530925.616538,"te":1500530925.685676,"ottl":128,"ittl":88,"otcp_win":8192,"itcp_win":28200,"otcp_syn":32,"otcp_nop":3,"itcp_nop":3,"otcp_mss":1460,"itcp_mss":1410,"otcp_wscale":8,"itcp_wscale":8,"otcp_sack":1,"itcp_sack":1,"packets":[{"b":200,"dir":">","ipt":1},{"b":1410,"dir":"<","ipt":2},{"b":1410,"dir":"<","ipt":0},{"b":669,"dir":"<","ipt":0},{"b":126,"dir":">","ipt":27},{"b":258,"dir":"<","ipt":1},{"b":81,"dir":"<","ipt":0}],"bd":[163,98,58,97,76,47,85,27,32,17,23,27,20,25,24,12,20,12,11,30,22,17,25,20,9,8,8,4,19,28,10,11,30,13,4,9,6,7,18,12,18,10,25,24,5,16,66,38,123,41,26,5,10,9,8,9,9,8,15,16,8,9,10,6,12,27,17,25,17,10,9,12,27,12,11,6,8,5,9,7,9,8,5,21,3,44,14,12,11,12,11,9,10,6,12,11,8,24,27,67,26,64,24,38,33,54,6,14,18,32,28,48,17,7,62,29,52,21,21,24,12,10,10,6,10,8,10,6,8,11,37,10,12,13,27,11,8,14,11,11,7,7,5,3,10,9,12,8,11,9,5,3,14,11,13,10,14,8,15,7,16,8,12,12,12,8,10,11,9,8,15,8,11,7,4,13,12,7,8,8,12,7,10,11,8,9,13,6,3,8,7,13,18,5,14,10,10,6,7,14,8,7,5,10,12,6,11,4,11,4,6,18,7,10,5,14,8,12,11,1,11,9,6,13,9,8,7,13,4,14,7,11,7,2,11,6,4,14,5,11,4,11,12,6,5,13,3,13,7,8,7,9,5,16,4,19],"bd_mean":0.000000,"bd_std":0.000000,"tls":{"tls_ov":3,"tls_iv":5,"tls_client_key_length":528,"clientKeyExchange":"41042742c5713f2d17f956ad15664f8983f550415e9056fd283b8b0bea7ae88c253d2bb46ef3b83bfd5c8d3be92b94ddd9bfeb8bec2419c0c36657ea14e6733b08e2","tls_crandom":"8a641777a4ce7f10725c9ebda5b5e7e84cccda46b4140889b4159cd71efdf43e","tls_srandom":"a55dc2d180d326d3a898de581b56e1c10404d3022103b3d4bd3079669c43bbc0","SNI":["facebook.com"],"cs":["8a8a","c02b","c02f","c02c","c030","cca9","cca8","c013","c014","009c","009d","002f","0035","000a"],"scs":"c02b","tls_ext":[{"type":"1a1a","length":0,"data":""},{"type":"ff01","length":1,"data":"00"},{"type":"0017","length":0,"data":""},{"type":"0023","length":0,"data":""},{"type":"000d","length":20,"data":"0012040308040401050308050501080606010201"},{"type":"0005","length":5,"data":"0100000000"},{"type":"0012","length":0,"data":""},{"type":"0010","length":14,"data":"000c02683208687474702f312e31"},{"type":"7550","length":0,"data":""},{"type":"000b","length":2,"data":"0100"},{"type":"000a","length":10,"data":"00086a6a001d00170018"},{"type":"7a7a","length":1,"data":"00"}],"s_tls_ext":[{"type":"0000","length":0,"data":""},{"type":"ff01","length":1,"data":"00"},{"type":"000b","length":4,"data":"03000102"},{"type":"0023","length":0,"data":""},{"type":"0010","length":5,"data":"0003026832"}],"server_cert":[{"length":2024,"serial_number":"0c0099b7d789c9f66626317ebcea7c1c","signature":"2a864886f70d01010b","issuer":[{"issuer_id":"550406","issuer_string":"US"},{"issuer_id":"55040a","issuer_string":"DigiCert Inc"},{"issuer_id":"55040b","issuer_string":"www.digicert.com"},{"issuer_id":"550403","issuer_string":"DigiCert SHA2 High Assurance Server CA"}],"validity_not_before":"161209000000Z","validity_not_after":"180125120000Z","subject":[{"subject_id":"550406","subject_string":"US"},{"subject_id":"550408","subject_string":"California"},{"subject_id":"550407","subject_string":"Menlo Park"},{"subject_id":"55040a","subject_string":"Facebook, Inc."},{"subject_id":"550403","subject_string":"*.facebook.com"}]}],"srlt":[{"b":195,"dir":">","ipt":0,"tp":"22:1"},{"b":74,"dir":"<","ipt":2,"tp":"22:2"},{"b":3242,"dir":"<","ipt":0,"tp":"22:11"},{"b":70,"dir":">","ipt":27,"tp":"22:16"},{"b":1,"dir":">","ipt":0,"tp":"20:0"},{"b":40,"dir":">","ipt":0,"tp":"22:0"},{"b":76,"dir":"<","ipt":1,"tp":"23:0"}]}}
{"sa":"10.144.94.253","da":"31.13.95.36","pr":6,"sp":64043,"dp":443,"ob":3097,"op":130,"ib":384917,"ip":333,"ts":1500530925.616632,"te":1500530934.307356,"ottl":128,"ittl":90,"otcp_win":8192,"itcp_win":28200,"otcp_syn":32,"otcp_nop":3,"itcp_nop":3,"otcp_mss":1460,"itcp_mss":1410,"otcp_wscale":8,"itcp_wscale":8,"otcp_sack":1,"itcp_sack":1,"packets":[{"b":200,"dir":">","ipt":1},{"b":1410,"dir":"<","ipt":1},{"b":1410,"dir":"<","ipt":0},{"b":669,"dir":"<","ipt":0},{"b":126,"dir":">","ipt":3},{"b":258,"dir":"<","ipt":1},{"b":81,"dir":"<","ipt":0},{"b":53,"dir":">","ipt":60},{"b":56,"dir":">","ipt":0},{"b":42,"dir":">","ipt":0},{"b":38,"dir":">","ipt":0},{"b":260,"dir":">","ipt":0},{"b":38,"dir":"<","ipt":0},{"b":186,"dir":"<","ipt":0},{"b":65,"dir":">","ipt":21},{"b":42,"dir":"<","ipt":1},{"b":42,"dir":"<","ipt":51},{"b":1410,"dir":"<","ipt":157},{"b":119,"dir":"<","ipt":0},{"b":354,"dir":"<","ipt":0},{"b":1410,"dir":"<","ipt":0},{"b":119,"dir":"<","ipt":0},{"b":1302,"dir":"<","ipt":0},{"b":1410,"dir":"<","ipt":0},{"b":119,"dir":"<","ipt":0},{"b":1410,"dir":"<","ipt":0},{"b":1200,"dir":"<","ipt":0},{"b":1410,"dir":"<","ipt":1},{"b":1410,"dir":"<","ipt":0},{"b":1410,"dir":"<","ipt":0},{"b":1410,"dir":"<","ipt":0},{"b":1410,"dir":"<","ipt":0},{"b":1410,"dir":"<","ipt":0},{"b":1410,"dir":"<","ipt":0},{"b":1410,"dir":"<","ipt":0},{"b":1410,"dir":"<","ipt":0},{"b":1410,"dir":"<","ipt":0},{"b":1410,"dir":"<","ipt":0},{"b":1410,"dir":"<","ipt":0},{"b":1410,"dir":"<","ipt":0},{"b":1410,"dir":"<","ipt":0},{"b":1410,"dir":"<","ipt":0},{"b":1410,"dir":"<","ipt":0},{"b":1410,"dir":"<","ipt":0},{"b":1410,"dir":"<","ipt":0},{"b":1410,"dir":"<","ipt":0},{"b":1410,"dir":"<","ipt":0},{"b":617,"dir":"<","ipt":0},{"b":1410,"dir":"<","ipt":0},{"b":460,"dir":"<","ipt":0},{"b":57,"dir":"<","ipt":0},{"b":39,"dir":"<","ipt":0},{"b":195,"dir":">","ipt":19},{"b":91,"dir":">","ipt":0},{"b":89,"dir":">","ipt":0},{"b":42,"dir":"<","ipt":1},{"b":42,"dir":"<","ipt":0},{"b":42,"dir":"<","ipt":0},{"b":1410,"dir":"<","ipt":0},{"b":119,"dir":"<","ipt":0},{"b":1410,"dir":"<","ipt":0},{"b":116,"dir":">","ipt":34},{"b":85,"dir":">","ipt":4},{"b":135,"dir":">","ipt":47},{"b":134,"dir":">","ipt":8},{"b":85,"dir":">","ipt":2},{"b":197,"dir":">","ipt":131},{"b":97,"dir":">","ipt":0},{"b":88,"dir":">","ipt":0},{"b":97,"dir":">","ipt":0},{"b":88,"dir":">","ipt":0},{"b":97,"dir":">","ipt":0},{"b":97,"dir":">","ipt":21},{"b":97,"dir":">","ipt":0},{"b":88,"dir":">","ipt":0},{"b":88,"dir":">","ipt":92},{"b":96,"dir":">","ipt":65},{"b":85,"dir":">","ipt":29},{"b":112,"dir":">","ipt":7925}],"bd":[233,210,213,239,204,216,200,194,182,188,194,183,183,191,184,192,187,188,188,198,186,189,191,220,193,179,189,191,179,192,190,185,200,186,180,181,189,196,187,199,186,178,188,196,187,189,196,192,201,196,192,183,190,187,193,188,179,181,186,190,181,176,188,186,181,190,190,188,179,190,181,182,181,192,195,191,187,187,193,189,186,192,187,201,193,185,181,186,189,184,184,192,183,183,196,182,189,179,191,193,195,195,192,191,192,194,195,181,190,190,197,180,187,190,192,180,198,173,196,193,193,188,185,190,187,183,185,187,189,185,198,191,181,189,190,193,193,183,183,196,186,188,187,216,180,182,186,185,191,192,196,183,194,188,181,187,185,188,181,185,194,181,191,179,189,189,190,189,193,190,180,210,192,180,184,187,187,184,183,190,190,189,186,186,188,192,206,190,180,189,186,193,185,190,182,189,187,183,188,182,184,193,189,186,196,192,183,183,184,188,188,192,191,190,191,182,196,187,185,184,192,188,186,186,183,191,191,188,182,184,191,185,182,186,205,185,176,180,185,186,186,188,191,187,193,190,188,191,188,181,183,190,203,182,187,184],"bd_mean":0.000000,"bd_std":0.000000,"tls":{"tls_ov":3,"tls_iv":5,"tls_client_key_length":528,"clientKeyExchange":"410425f936e04e4d99acf712b5c327dc3395d48a1d5305b3a4ff7206dc121362d2e99ebff547005d91697c7c0f7854167a0f83df5946d6afec56a527ae2855557ee8","tls_crandom":"6b94023d310d65667cd060a28a7ac35f6af60ecae7f72991cccf1b93f09bf30f","tls_srandom":"c5018ef87df089823b130666dd10028d76eafee6b306c29c25c680645ff6795b","SNI":["facebook.com"],"cs":["6a6a","c02b","c02f","c02c","c030","cca9","cca8","c013","c014","009c","009d","002f","0035","000a"],"scs":"c02b","tls_ext":[{"type":"0a0a","length":0,"data":""},{"type":"ff01","length":1,"data":"00"},{"type":"0017","length":0,"data":""},{"type":"0023","length":0,"data":""},{"type":"000d","length":20,"data":"0012040308040401050308050501080606010201"},{"type":"0005","length":5,"data":"0100000000"},{"type":"0012","length":0,"data":""},{"type":"0010","length":14,"data":"000c02683208687474702f312e31"},{"type":"7550","length":0,"data":""},{"type":"000b","length":2,"data":"0100"},{"type":"000a","length":10,"data":"00089a9a001d00170018"},{"type":"3a3a","length":1,"data":"00"}],"s_tls_ext":[{"type":"0000","length":0,"data":""},{"type":"ff01","length":1,"data":"00"},{"type":"000b","length":4,"data":"03000102"},{"type":"0023","length":0,"data":""},{"type":"0010","length":5,"data":"0003026832"}],"server_cert":[{"length":2024,"serial_number":"0c0099b7d789c9f66626317ebcea7c1c","signature":"2a864886f70d01010b","issuer":[{"issuer_id":"550406","issuer_string":"US"},{"issuer_id":"55040a","issuer_string":"DigiCert Inc"},{"issuer_id":"55040b","issuer_string":"www.digicert.com"},{"issuer_id":"550403","issuer_string":"DigiCert SHA2 High Assurance Server CA"}],"validity_not_before":"161209000000Z","validity_not_after":"180125120000Z","subject":[{"subject_id":"550406","subject_string":"US"},{"subject_id":"550408","subject_string":"California"},{"subject_id":"550407","subject_string":"Menlo Park"},{"subject_id":"55040a","subject_string":"Facebook, Inc."},{"subject_id":"550403","subject_string":"*.facebook.com"}]}],"srlt":[{"b":195,"dir":">","ipt":0,"tp":"22:1"},{"b":74,"dir":"<","ipt":1,"tp":"22:2"},{"b":3242,"dir":"<","ipt":0,"tp":"22:11"},{"b":70,"dir":">","ipt":3,"tp":"22:16"},{"b":1,"dir":">","ipt":0,"tp":"20:0"},{"b":40,"dir":">","ipt":0,"tp":"22:0"},{"b":76,"dir":"<","ipt":1,"tp":"23:0"},{"b":48,"dir":">","ipt":60,"tp":"23:0"},{"b":51,"dir":">","ipt":0,"tp":"23:0"},{"b":37,"dir":">","ipt":0,"tp":"23:0"},{"b":33,"dir":">","ipt":0,"tp":"23:0"},{"b":255,"dir":">","ipt":0,"tp":"23:0"},{"b":33,"dir":"<","ipt":0,"tp":"23:0"},{"b":181,"dir":"<","ipt":0,"tp":"23:0"},{"b":60,"dir":">","ipt":21,"tp":"23:0"},{"b":37,"dir":"<","ipt":1,"tp":"23:0"},{"b":37,"dir":"<","ipt":51,"tp":"23:0"},{"b":1524,"dir":"<","ipt":157,"tp":"23:0"},{"b":349,"dir":"<","ipt":0,"tp":"23:0"},{"b":1524,"dir":"<","ipt":0,"tp":"23:0"},{"b":1297,"dir":"<","ipt":0,"tp":"23:0"},{"b":1524,"dir":"<","ipt":0,"tp":"23:0"},{"b":2605,"dir":"<","ipt":0,"tp":"23:0"},{"b":4096,"dir":"<","ipt":1,"tp":"23:0"},{"b":1865,"dir":"<","ipt":1,"tp":"23:0"},{"b":52,"dir":"<","ipt":0,"tp":"23:0"},{"b":34,"dir":"<","ipt":0,"tp":"23:0"},{"b":190,"dir":">","ipt":19,"tp":"23:0"},{"b":86,"dir":">","ipt":0,"tp":"23:0"},{"b":84,"dir":">","ipt":0,"tp":"23:0"},{"b":37,"dir":"<","ipt":1,"tp":"23:0"},{"b":37,"dir":"<","ipt":0,"tp":"23:0"},{"b":37,"dir":"<","ipt":0,"tp":"23:0"},{"b":1524,"dir":"<","ipt":0,"tp":"23:0"},{"b":8024,"dir":"<","ipt":0,"tp":"23:0"},{"b":7224,"dir":"<","ipt":0,"tp":"23:0"},{"b":1524,"dir":"<","ipt":0,"tp":"23:0"},{"b":111,"dir":">","ipt":33,"tp":"23:0"},{"b":37,"dir":"<","ipt":1,"tp":"23:0"},{"b":1524,"dir":"<","ipt":0,"tp":"23:0"},{"b":8024,"dir":"<","ipt":0,"tp":"23:0"},{"b":7119,"dir":"<","ipt":0,"tp":"23:0"},{"b":1524,"dir":"<","ipt":0,"tp":"23:0"},{"b":8024,"dir":"<","ipt":0,"tp":"23:0"},{"b":6917,"dir":"<","ipt":0,"tp":"23:0"},{"b":80,"dir":">","ipt":2,"tp":"23:0"},{"b":37,"dir":"<","ipt":1,"tp":"23:0"},{"b":758,"dir":"<","ipt":0,"tp":"23:0"},{"b":130,"dir":">","ipt":46,"tp":"23:0"},{"b":37,"dir":"<","ipt":1,"tp":"23:0"},{"b":1524,"dir":"<","ipt":0,"tp":"23:0"},{"b":8024,"dir":"<","ipt":0,"tp":"23:0"},{"b":37880,"dir":"<","ipt":0,"tp":"21:0"},{"b":3715,"dir":"<","ipt":0,"tp":"23:0"},{"b":129,"dir":">","ipt":6,"tp":"23:0"},{"b":37,"dir":"<","ipt":1,"tp":"23:0"},{"b":947,"dir":"<","ipt":0,"tp":"23:0"},{"b":80,"dir":">","ipt":0,"tp":"23:0"},{"b":37,"dir":"<","ipt":1,"tp":"23:0"},{"b":1524,"dir":"<","ipt":0,"tp":"23:0"},{"b":192,"dir":">","ipt":129,"tp":"23:0"},{"b":92,"dir":">","ipt":0,"tp":"23:0"},{"b":83,"dir":">","ipt":0,"tp":"23:0"},{"b":92,"dir":">","ipt":0,"tp":"23:0"},{"b":83,"dir":">","ipt":0,"tp":"23:0"},{"b":92,"dir":">","ipt":0,"tp":"23:0"},{"b":37,"dir":"<","ipt":0,"tp":"23:0"},{"b":37,"dir":"<","ipt":0,"tp":"23:0"},{"b":37,"dir":"<","ipt":0,"tp":"23:0"},{"b":37,"dir":"<","ipt":0,"tp":"23:0"},{"b":37,"dir":"<","ipt":0,"tp":"23:0"},{"b":1524,"dir":"<","ipt":0,"tp":"23:0"},{"b":3238,"dir":"<","ipt":0,"tp":"23:0"},{"b":1524,"dir":"<","ipt":0,"tp":"23:0"},{"b":92,"dir":">","ipt":18,"tp":"23:0"},{"b":92,"dir":">","ipt":0,"tp":"23:0"},{"b":83,"dir":">","ipt":0,"tp":"23:0"},{"b":83,"dir":">","ipt":92,"tp":"23:0"},{"b":91,"dir":">","ipt":65,"tp":"23:0"},{"b":80,"dir":">","ipt":29,"tp":"23:0"},{"b":107,"dir":">","ipt":7925,"tp":"23:0"}]}}
{"sa":"10.144.94.253","da":"31.13.95.36","pr":6,"sp":64044,"dp":443,"ob":330,"op":8,"ib":3827,"ip":7,"ts":1500530925.689789,"te":1500530925.709052,"ottl":128,"ittl":90,"otcp_win":8192,"itcp_win":28200,"otcp_syn":32,"otcp_nop":3,"itcp_nop":3,"otcp_mss":1460,"itcp_mss":1410,"otcp_wscale":8,"itcp_wscale":8,"otcp_sack":1,"itcp_sack":1,"packets":[{"b":204,"dir":">","ipt":1},{"b":1410,"dir":"<","ipt":2},{"b":1410,"dir":"<","ipt":0},{"b":668,"dir":"<","ipt":0},{"b":126,"dir":">","ipt":3},{"b":258,"dir":"<","ipt":1},{"b":81,"dir":"<","ipt":0}],"bd":[163,100,55,96,75,47,87,29,32,19,26,25,21,26,27,9,21,14,14,33,23,17,26,21,10,9,8,9,19,26,10,13,31,10,6,9,8,6,17,14,17,11,23,21,4,14,67,36,124,39,26,7,9,9,10,7,13,7,18,12,10,9,11,3,14,27,14,24,17,14,7,19,24,10,9,11,9,7,12,9,10,7,5,23,3,44,10,10,10,11,19,8,10,4,9,13,6,24,31,67,25,65,22,37,36,54,4,18,17,32,28,48,24,6,61,27,55,22,21,26,13,7,8,6,5,8,10,7,9,14,37,7,12,14,30,9,5,9,10,16,8,7,4,5,8,7,9,8,9,7,8,8,11,12,14,10,12,6,11,9,15,13,10,14,12,5,10,10,7,8,16,10,11,4,7,8,12,6,7,7,8,5,9,14,7,9,16,7,4,8,7,12,17,4,11,10,9,4,7,15,8,9,6,9,10,7,10,6,10,3,7,15,6,12,8,12,8,10,13,2,11,8,3,12,7,9,6,10,5,15,5,10,4,6,13,4,6,12,11,12,6,9,9,3,5,13,4,10,4,13,7,8,5,16,7,17],"bd_mean":0.000000,"bd_std":0.000000,"tls":{"tls_ov":3,"tls_iv":5,"tls_client_key_length":528,"clientKeyExchange":"4104df688d6cef0fbf411215dd27b09b60501a30fa3df006d3ade712f481d6a1f08614cd4cf7513b0a75e2c64501295e5c1f96d71262f15a70a836451da45f4b47af","tls_crandom":"ec995be968b3388520360c5c1136c398d87a1ec08c3a4c8b3b8b0afdf6100eb9","tls_srandom":"56d4e9cba284625b9b108a1b868a13f5430830ac3c648c663e0dfd5f8b431bd8","SNI":["www.facebook.com"],"cs":["eaea","c02b","c02f","c02c","c030","cca9","cca8","c013","c014","009c","009d","002f","0035","000a"],"scs":"c02b","tls_ext":[{"type":"5a5a","length":0,"data":""},{"type":"ff01","length":1,"data":"00"},{"type":"0017","length":0,"data":""},{"type":"0023","length":0,"data":""},{"type":"000d","length":20,"data":"0012040308040401050308050501080606010201"},{"type":"0005","length":5,"data":"0100000000"},{"type":"0012","length":0,"data":""},{"type":"0010","length":14,"data":"000c02683208687474702f312e31"},{"type":"7550","length":0,"data":""},{"type":"000b","length":2,"data":"0100"},{"type":"000a","length":10,"data":"00089a9a001d00170018"},{"type":"eaea","length":1,"data":"00"}],"s_tls_ext":[{"type":"0000","length":0,"data":""},{"type":"ff01","length":1,"data":"00"},{"type":"000b","length":4,"data":"03000102"},{"type":"0023","length":0,"data":""},{"type":"0010","length":5,"data":"0003026832"}],"server_cert":[{"length":2024,"serial_number":"0c0099b7d789c9f66626317ebcea7c1c","signature":"2a864886f70d01010b","issuer":[{"issuer_id":"550406","issuer_string":"US"},{"issuer_id":"55040a","issuer_string":"DigiCert Inc"},{"issuer_id":"55040b","issuer_string":"www.digicert.com"},{"issuer_id":"550403","issuer_string":"DigiCert SHA2 High Assurance Server CA"}],"validity_not_before":"161209000000Z","validity_not_after":"180125120000Z","subject":[{"subject_id":"550406","subject_string":"US"},{"subject_id":"550408","subject_string":"California"},{"subject_id":"550407","subject_string":"Menlo Park"},{"subject_id":"55040a","subject_string":"Facebook, Inc."},{"subject_id":"550403","subject_string":"*.facebook.com"}]}],"srlt":[{"b":199,"dir":">","ipt":0,"tp":"22:1"},{"b":74,"dir":"<","ipt":2,"tp":"22:2"},{"b":3242,"dir":"<","ipt":0,"tp":"22:11"},{"b":70,"dir":">","ipt":3,"tp":"22:16"},{"b":1,"dir":">","ipt":0,"tp":"20:0"},{"b":40,"dir":">","ipt":0,"tp":"22:0"},{"b":76,"dir":"<","ipt":1,"tp":"23:0"}]}}
{"sa":"10.144.94.253","da":"31.13.95.36","pr":6,"sp":64045,"dp":443,"ob":330,"op":6,"ib":3826,"ip":7,"ts":1500530925.689877,"te":1500530925.702031,"ottl":128,"ittl":88,"otcp_win":8192,"itcp_win":28200,"otcp_syn":32,"otcp_nop":3,"itcp_nop":3,"otcp_mss":1460,"itcp_mss":1410,"otcp_wscale":8,"itcp_wscale":8,"otcp_sack":1,"itcp_sack":1,"packets":[{"b":204,"dir":">","ipt":1},{"b":1410,"dir":"<","ipt":2},{"b":1410,"dir":"<","ipt":0},{"b":667,"dir":"<","ipt":0},{"b":126,"dir":">","ipt":6},{"b":258,"dir":"<","ipt":1},{"b":81,"dir":"<","ipt":0}],"bd":[162,97,58,95,74,48,84,29,28,18,24,26,19,26,22,9,18,13,10,33,22,16,29,21,11,10,9,5,15,27,10,12,34,14,5,11,7,8,16,10,15,12,24,20,4,15,68,36,122,45,27,7,9,9,8,8,12,10,15,11,9,9,10,3,13,26,21,24,18,12,7,15,24,14,14,8,7,7,7,9,10,7,4,20,6,44,13,12,11,15,13,7,9,7,10,12,8,26,28,68,24,65,21,39,35,54,4,18,17,32,28,48,18,7,62,27,57,17,19,28,11,8,8,7,6,9,13,8,7,13,36,7,10,11,28,9,6,14,11,11,9,8,4,7,7,10,10,12,11,12,6,6,13,13,12,9,11,6,13,7,17,8,8,15,13,7,9,14,6,9,12,9,11,5,7,9,14,8,9,9,11,5,11,14,8,7,14,6,6,11,4,13,16,5,10,9,11,6,10,16,7,6,5,10,13,5,14,5,11,1,7,18,7,11,7,10,6,16,11,3,11,8,5,10,9,13,7,11,4,15,6,10,4,5,7,3,8,11,6,12,5,8,8,5,9,15,9,11,5,11,6,8,4,12,5,17],"bd_mean":0.000000,"bd_std":0.000000,"tls":{"tls_ov":3,"tls_iv":5,"tls_client_key_length":528,"clientKeyExchange":"410450cd4300af59ade1e20ad4aeabd3ec767cae252e363697f76d89dac9cc2ebb6bb2c1a721b4b551897520aa747f666759d2b86b8667ec5aa34dccf90c42f28fb0","tls_crandom":"4c8b324de7feb2648766bee6a4158ca051bf5d39884bb0a5d5c4425df00c314a","tls_srandom":"ab0398388691f4d0f0a86337207423d68931fec1e17358ed591616efc311baa0","SNI":["www.facebook.com"],"cs":["4a4a","c02b","c02f","c02c","c030","cca9","cca8","c013","c014","009c","009d","002f","0035","000a"],"scs":"c02b","tls_ext":[{"type":"3a3a","length":0,"data":""},{"type":"ff01","length":1,"data":"00"},{"type":"0017","length":0,"data":""},{"type":"0023","length":0,"data":""},{"type":"000d","length":20,"data":"0012040308040401050308050501080606010201"},{"type":"0005","length":5,"data":"0100000000"},{"type":"0012","length":0,"data":""},{"type":"0010","length":14,"data":"000c02683208687474702f312e31"},{"type":"7550","length":0,"data":""},{"type":"000b","length":2,"data":"0100"},{"type":"000a","length":10,"data":"00088a8a001d00170018"},{"type":"4a4a","length":1,"data":"00"}],"s_tls_ext":[{"type":"0000","length":0,"data":""},{"type":"ff01","length":1,"data":"00"},{"type":"000b","length":4,"data":"03000102"},{"type":"0023","length":0,"data":""},{"type":"0010","length":5,"data":"0003026832"}],"server_cert":[{"length":2024,"serial_number":"0c0099b7d789c9f66626317ebcea7c1c","signature":"2a864886f70d01010b","issuer":[{"issuer_id":"550406","issuer_string":"US"},{"issuer_id":"55040a","issuer_string":"DigiCert Inc"},{"issuer_id":"55040b","issuer_string":"www.digicert.com"},{"issuer_id":"550403","issuer_string":"DigiCert SHA2 High Assurance Server CA"}],"validity_not_before":"161209000000Z","validity_not_after":"180125120000Z","subject":[{"subject_id":"550406","subject_string":"US"},{"subject_id":"550408","subject_string":"California"},{"subject_id":"550407","subject_string":"Menlo Park"},{"subject_id":"55040a","subject_string":"Facebook, Inc."},{"subject_id":"550403","subject_string":"*.facebook.com"}]}],"srlt":[{"b":199,"dir":">","ipt":0,"tp":"22:1"},{"b":74,"dir":"<","ipt":2,"tp":"22:2"},{"b":3242,"dir":"<","ipt":0,"tp":"22:11"},{"b":70,"dir":">","ipt":6,"tp":"22:16"},{"b":1,"dir":">","ipt":0,"tp":"20:0"},{"b":40,"dir":">","ipt":0,"tp":"22:0"},{"b":76,"dir":"<","ipt":1,"tp":"23:0"}]}}
{"sa":"10.144.94.253","da":"31.13.95.12","pr":6,"sp":64047,"dp":443,"ob":984,"op":13,"ib":4846,"ip":11,"ts":1500530926.313184,"te":1500530926.384596,"ottl":128,"ittl":88,"otcp_win":8192,"itcp_win":28200,"otcp_syn":32,"otcp_nop":3,"itcp_nop":3,"otcp_mss":1460,"itcp_mss":1410,"otcp_wscale":8,"itcp_wscale":8,"otcp_sack":1,"itcp_sack":1,"packets":[{"b":209,"dir":">","ipt":1},{"b":1410,"dir":"<","ipt":2},{"b":1410,"dir":"<","ipt":0},{"b":668,"dir":"<","ipt":0},{"b":126,"dir":">","ipt":3},{"b":258,"dir":"<","ipt":1},{"b":81,"dir":"<","ipt":0},{"b":53,"dir":">","ipt":13},{"b":56,"dir":">","ipt":0},{"b":42,"dir":">","ipt":0},{"b":38,"dir":">","ipt":0},{"b":460,"dir":">","ipt":0},{"b":38,"dir":"<","ipt":1},{"b":42,"dir":"<","ipt":0},{"b":939,"dir":"<","ipt":0}],"bd":[211,104,62,119,82,49,92,35,33,24,27,31,25,37,25,14,18,16,18,41,27,21,29,35,17,17,14,15,26,35,17,26,45,20,7,12,16,15,20,15,24,19,33,27,9,28,74,45,133,44,32,11,19,19,12,13,17,14,23,19,18,16,20,9,21,34,22,30,24,18,8,24,24,22,20,15,14,14,16,12,16,10,11,24,13,48,14,22,20,17,20,15,14,14,27,20,16,30,35,76,35,71,25,42,36,59,8,24,22,34,37,51,23,14,65,33,63,24,23,27,28,17,13,9,10,16,18,14,17,21,41,16,20,23,38,13,15,15,21,17,15,14,14,8,12,17,15,25,22,15,14,7,18,25,13,16,20,11,18,9,23,18,15,21,17,12,23,19,18,17,21,14,18,14,13,19,24,11,15,13,15,13,21,23,14,10,19,12,9,15,10,18,21,10,13,14,13,9,12,19,16,21,18,17,21,14,22,10,17,9,12,18,11,13,14,16,11,17,20,10,19,16,9,15,17,14,11,23,14,28,18,17,10,10,13,12,9,14,11,14,11,14,25,12,12,19,10,16,13,20,8,15,11,17,9,26],"bd_mean":0.000000,"bd_std":0.000000,"tls":{"tls_ov":3,"tls_iv":5,"tls_client_key_length":528,"clientKeyExchange":"41048f2bd79d7932ee3342cda2cb9c854aa21e4b78d9171c9cf4857917e8288e37008ee32f06e0663660cd1e793b296cc2fe503404b2e3f01913801d38a65efd40c1","tls_crandom":"7ac94aff8a20083288bd548a30e334855fa7731e8e497d36111fb071856289d1","tls_srandom":"19241fdf8e4d11b32b3d70100709ed4b77c9bdea4c32582507695f599e5eb098","SNI":["staticxx.facebook.com"],"cs":["7a7a","c02b","c02f","c02c","c030","cca9","cca8","c013","c014","009c","009d","002f","0035","000a"],"scs":"c02b","tls_ext":[{"type":"4a4a","length":0,"data":""},{"type":"ff01","length":1,"data":"00"},{"type":"0017","length":0,"data":""},{"type":"0023","length":0,"data":""},{"type":"000d","length":20,"data":"0012040308040401050308050501080606010201"},{"type":"0005","length":5,"data":"0100000000"},{"type":"0012","length":0,"data":""},{"type":"0010","length":14,"data":"000c02683208687474702f312e31"},{"type":"7550","length":0,"data":""},{"type":"000b","length":2,"data":"0100"},{"type":"000a","length":10,"data":"0008caca001d00170018"},{"type":"fafa","length":1,"data":"00"}],"s_tls_ext":[{"type":"0000","length":0,"data":""},{"type":"ff01","length":1,"data":"00"},{"type":"000b","length":4,"data":"03000102"},{"type":"0023","length":0,"data":""},{"type":"0010","length":5,"data":"0003026832"}],"server_cert":[{"length":2024,"serial_number":"0c0099b7d789c9f66626317ebcea7c1c","signature":"2a864886f70d01010b","issuer":[{"issuer_id":"550406","issuer_string":"US"},{"issuer_id":"55040a","issuer_string":"DigiCert Inc"},{"issuer_id":"55040b","issuer_string":"www.digicert.com"},{"issuer_id":"550403","issuer_string":"DigiCert SHA2 High Assurance Server CA"}],"validity_not_before":"161209000000Z","validity_not_after":"180125120000Z","subject":[{"subject_id":"550406","subject_string":"US"},{"subject_id":"550408","subject_string":"California"},{"subject_id":"550407","subject_string":"Menlo Park"},{"subject_id":"55040a","subject_string":"Facebook, Inc."},{"subject_id":"550403","subject_string":"*.facebook.com"}]}],"srlt":[{"b":204,"dir":">","ipt":0,"tp":"22:1"},{"b":74,"dir":"<","ipt":2,"tp":"22:2"},{"b":3242,"dir":"<","ipt":0,"tp":"22:11"},{"b":70,"dir":">","ipt":3,"tp":"22:16"},{"b":1,"dir":">","ipt":0,"tp":"20:0"},{"b":40,"dir":">","ipt":0,"tp":"22:0"},{"b":76,"dir":"<","ipt":1,"tp":"23:0"},{"b":48,"dir":">","ipt":13,"tp":"23:0"},{"b":51,"dir":">","ipt":0,"tp":"23:0"},{"b":37,"dir":">","ipt":0,"tp":"23:0"},{"b":33,"dir":">","ipt":0,"tp":"23:0"},{"b":455,"dir":">","ipt":0,"tp":"23:0"},{"b":33,"dir":"<","ipt":1,"tp":"23:0"},{"b":37,"dir":"<","ipt":0,"tp":"23:0"},{"b":934,"dir":"<","ipt":0,"tp":"23:0"}]}}
{"sa":"10.144.94.253","da":"31.13.95.12","pr":6,"sp":64048,"dp":443,"ob":335,"op":9,"ib":3872,"ip":8,"ts":1500530926.313259,"te":1500530926.336492,"ottl":128,"ittl":88,"otcp_win":8192,"itcp_win":28200,"otcp_syn":32,"otcp_nop":3,"itcp_nop":3,"otcp_mss":1460,"itcp_mss":1410,"otcp_wscale":8,"itcp_wscale":8,"otcp_sack":1,"itcp_sack":1,"packets":[{"b":209,"dir":">","ipt":1},{"b":1410,"dir":"<","ipt":2},{"b":1410,"dir":"<","ipt":0},{"b":667,"dir":"<","ipt":0},{"b":126,"dir":">","ipt":9},{"b":258,"dir":"<","ipt":1},{"b":81,"dir":"<","ipt":0},{"b":46,"dir":"<","ipt":7}],"bd":[169,99,55,96,77,48,84,28,32,17,23,25,18,24,23,10,19,17,12,30,22,13,28,21,13,8,9,4,17,27,9,11,30,9,5,12,9,8,15,11,16,10,25,22,5,15,69,35,123,40,27,6,10,7,6,10,11,7,21,16,12,9,13,6,13,24,13,22,23,13,8,16,25,14,11,8,6,6,9,5,9,8,7,24,3,48,11,10,13,12,14,8,9,6,10,12,8,30,28,69,28,65,22,39,34,54,5,15,16,33,27,49,21,8,64,28,57,21,23,22,16,9,15,9,5,8,10,8,9,13,39,8,14,11,25,7,5,10,9,10,7,11,6,6,7,10,12,12,10,11,8,6,12,13,13,9,12,8,14,8,16,14,8,14,13,4,11,11,6,12,18,6,11,5,11,7,10,9,8,8,9,6,10,12,13,10,13,7,4,8,8,11,17,5,14,8,11,3,9,12,8,7,9,7,11,5,13,4,15,3,6,14,5,11,8,10,6,15,11,6,11,9,8,8,7,11,7,14,5,15,7,9,4,1,9,4,7,16,8,11,6,10,11,2,7,14,8,11,5,11,5,8,8,11,5,19],"bd_mean":0.000000,"bd_std":0.000000,"tls":{"tls_ov":3,"tls_iv":5,"tls_client_key_length":528,"clientKeyExchange":"410463005ef088e623e25572fc9f81bb27475753b5e1c951933c9a802d513c11c005d8c2835c5446dc38f2f13f6fb917e3ec7160a9aa79ffa62edb4b673aa1404461","tls_crandom":"9e7070007e3e0167b8d6adaedbb905994a8d58e34469ea190fdbffb6a16408ec","tls_srandom":"5c2793291dd4046173998af0ebae90ee3689f280ae759aae170f953fc289301d","SNI":["staticxx.facebook.com"],"cs":["9a9a","c02b","c02f","c02c","c030","cca9","cca8","c013","c014","009c","009d","002f","0035","000a"],"scs":"c02b","tls_ext":[{"type":"7a7a","length":0,"data":""},{"type":"ff01","length":1,"data":"00"},{"type":"0017","length":0,"data":""},{"type":"0023","length":0,"data":""},{"type":"000d","length":20,"data":"0012040308040401050308050501080606010201"},{"type":"0005","length":5,"data":"0100000000"},{"type":"0012","length":0,"data":""},{"type":"0010","length":14,"data":"000c02683208687474702f312e31"},{"type":"7550","length":0,"data":""},{"type":"000b","length":2,"data":"0100"},{"type":"000a","length":10,"data":"00087a7a001d00170018"},{"type":"0a0a","length":1,"data":"00"}],"s_tls_ext":[{"type":"0000","length":0,"data":""},{"type":"ff01","length":1,"data":"00"},{"type":"000b","length":4,"data":"03000102"},{"type":"0023","length":0,"data":""},{"type":"0010","length":5,"data":"0003026832"}],"server_cert":[{"length":2024,"serial_number":"0c0099b7d789c9f66626317ebcea7c1c","signature":"2a864886f70d01010b","issuer":[{"issuer_id":"550406","issuer_string":"US"},{"issuer_id":"55040a","issuer_string":"DigiCert Inc"},{"issuer_id":"55040b","issuer_string":"www.digicert.com"},{"issuer_id":"550403","issuer_string":"DigiCert SHA2 High Assurance Server CA"}],"validity_not_before":"161209000000Z","validity_not_after":"180125120000Z","subject":[{"subject_id":"550406","subject_string":"US"},{"subject_id":"550408","subject_string":"California"},{"subject_id":"550407","subject_string":"Menlo Park"},{"subject_id":"55040a","subject_string":"Facebook, Inc."},{"subject_id":"550403","subject_string":"*.facebook.com"}]}],"srlt":[{"b":204,"dir":">","ipt":0,"tp":"22:1"},{"b":74,"dir":"<","ipt":2,"tp":"22:2"},{"b":3242,"dir":"<","ipt":0,"tp":"22:11"},{"b":70,"dir":">","ipt":9,"tp":"22:16"},{"b":1,"dir":">","ipt":0,"tp":"20:0"},{"b":40,"dir":">","ipt":0,"tp":"22:0"},{"b":76,"dir":"<","ipt":1,"tp":"23:0"},{"b":41,"dir":"<","ipt":7,"tp":"23:0"}]}}
{"sa":"10.144.94.253","da":"157.240.15.6","pr":6,"sp":64049,"dp":443,"ob":1106,"op":15,"ib":4870,"ip":14,"ts":1500530926.361534,"te":1500530926.447265,"ottl":128,"ittl":90,"otcp_win":8192,"itcp_win":28200,"otcp_syn":32,"otcp_nop":3,"itcp_nop":3,"otcp_mss":1460,"itcp_mss":1410,"otcp_wscale":8,"itcp_wscale":8,"otcp_sack":1,"itcp_sack":1,"packets":[{"b":200,"dir":">","ipt":1},{"b":1410,"dir":"<","ipt":2},{"b":1410,"dir":"<","ipt":0},{"b":845,"dir":"<","ipt":0},{"b":126,"dir":">","ipt":3},{"b":258,"dir":"<","ipt":1},{"b":81,"dir":"<","ipt":0},{"b":53,"dir":">","ipt":7},{"b":56,"dir":">","ipt":0},{"b":42,"dir":">","ipt":0},{"b":38,"dir":">","ipt":0},{"b":341,"dir":">","ipt":0},{"b":38,"dir":"<","ipt":0},{"b":42,"dir":"<","ipt":0},{"b":479,"dir":"<","ipt":31},{"b":38,"dir":"<","ipt":0},{"b":250,"dir":">","ipt":1},{"b":42,"dir":"<","ipt":1},{"b":227,"dir":"<","ipt":31}],"bd":[229,119,63,141,74,44,94,33,33,23,35,31,21,31,21,21,24,18,16,41,25,14,40,44,14,22,13,15,20,38,21,20,52,19,17,26,15,19,17,17,24,21,34,28,9,25,69,45,134,39,34,11,23,16,13,26,14,12,19,15,14,12,21,7,15,28,23,32,26,14,27,26,28,26,13,12,17,12,21,16,20,18,13,28,11,53,15,17,21,17,16,18,13,14,14,17,12,41,23,67,34,52,15,41,43,63,17,27,28,49,32,48,25,18,66,55,77,32,22,38,31,16,16,13,6,9,11,21,17,16,39,19,16,14,37,16,22,15,13,12,11,19,15,11,20,7,17,22,22,16,11,16,13,16,13,20,10,15,18,13,23,15,18,23,17,12,11,11,19,17,26,14,11,17,10,16,13,16,12,6,11,14,19,23,17,14,18,14,10,10,15,19,23,9,21,18,23,11,13,15,14,12,14,15,15,15,11,17,12,24,13,20,14,17,17,21,14,15,15,12,21,15,17,16,21,22,16,15,7,21,15,10,11,6,22,20,10,17,30,16,11,18,19,15,18,23,11,16,7,18,12,13,10,17,12,22],"bd_mean":0.000000,"bd_std":0.000000,"tls":{"tls_ov":3,"tls_iv":5,"tls_client_key_length":528,"clientKeyExchange":"410424f35bf9d4c0eb244720e39e65de74e421eefd3267b66d6b1011eca319d70c684dc901a8bdadb3f9db2fbfb6fd20baed524402735f7669b2cc0ee3fe35cc93cd","tls_crandom":"8036712d8d0fbe763e14ee55cf110975dd074e09bb7783bcd8af2f0103ded3bc","tls_srandom":"48a33a614b196f163e8604a1024339bddb503643426516addec24a618b0af991","SNI":["cx.atdmt.com"],"cs":["8a8a","c02b","c02f","c02c","c030","cca9","cca8","c013","c014","009c","009d","002f","0035","000a"],"scs":"c02f","tls_ext":[{"type":"7a7a","length":0,"data":""},{"type":"ff01","length":1,"data":"00"},{"type":"0017","length":0,"data":""},{"type":"0023","length":0,"data":""},{"type":"000d","length":20,"data":"0012040308040401050308050501080606010201"},{"type":"0005","length":5,"data":"0100000000"},{"type":"0012","length":0,"data":""},{"type":"0010","length":14,"data":"000c02683208687474702f312e31"},{"type":"7550","length":0,"data":""},{"type":"000b","length":2,"data":"0100"},{"type":"000a","length":10,"data":"00083a3a001d00170018"},{"type":"2a2a","length":1,"data":"00"}],"s_tls_ext":[{"type":"0000","length":0,"data":""},{"type":"ff01","length":1,"data":"00"},{"type":"000b","length":4,"data":"03000102"},{"type":"0023","length":0,"data":""},{"type":"0010","length":5,"data":"0003026832"}],"server_cert":[{"length":2016,"serial_number":"041e21ddd5ac2406dd24750aa5dc19cf","signature":"2a864886f70d01010b","signature_key_size":2048,"issuer":[{"issuer_id":"550406","issuer_string":"US"},{"issuer_id":"55040a","issuer_string":"DigiCert Inc"},{"issuer_id":"55040b","issuer_string":"www.digicert.com"},{"issuer_id":"550403","issuer_string":"DigiCert SHA2 High Assurance Server CA"}],"validity_not_before":"170427000000Z","validity_not_after":"180531120000Z","subject":[{"subject_id":"550406","subject_string":"US"},{"subject_id":"550408","subject_string":"California"},{"subject_id":"550407","subject_string":"Menlo Park"},{"subject_id":"55040a","subject_string":"Facebook, Inc."},{"subject_id":"550403","subject_string":"*.atlassolutions.com"}],"subject_public_key_algorithm":"2a864886f70d010101","subject_public_key_size":2048,"SAN":["*.atlassolutions.com","atlassolutions.com","*.atdmt.com","atdmt.com","*.atdmt2.com","atdmt2.com","*.atlassbx.com","atlassbx.com","*.xx.atlassbx.com","xx.atlassbx.com"],"extensions":[{"ext_id":"551d23","ext_data":"0418301680145168ff90af0207753cccd9656462a212b859723b"},{"ext_id":"551d0e","ext_data":"04160414795cb208aff1a9abfdeb997747728f5d4c8a07dc"},{"ext_id":"551d0f","ext_data":"0101ff0404030205a0"},{"ext_id":"551d25","ext_data":"0416301406082b0601050507030106082b06010505070302"},{"ext_id":"551d1f","ext_data":"046e306c3034a032a030862e687474703a2f2f63726c332e64696769636572742e636f6d2f736861322d68612d7365727665722d67352e63726c3034a032a030862e687474703a2f2f63726c342e64696769636572742e636f6d2f736861322d68612d7365727665722d67352e63726c"},{"ext_id":"551d20","ext_data":"04453043303706096086480186fd6c0101302a302806082b06010505070201161c68747470733a2f2f7777772e64696769636572742e636f6d2f4350533008060667810c010202"},{"ext_id":"2b06010505070101","ext_data":"04773075302406082b060105050730018618687474703a2f2f6f6373702e64696769636572742e636f6d304d06082b060105050730028641687474703a2f2f636163657274732e64696769636572742e636f6d2f446967694365727453484132486967684173737572616e636553657276657243412e637274"},{"ext_id":"551d13","ext_data":"0101ff04023000"},{"ext_id":"2b06010401d679020402","ext_data":"048201e5048201e101df007600a4b90990b418581487bb13a2cc67700a3c359804f91bdfb8e377cd0ec80ddc100000015bb0e5310d0000040300473045022100abcb367bc208dac41dbb84e6753482dbd619fe8aba7fed7aac49afbfa85c2b160220579b4bda5f96c529a0e1cd81171617bf31fb0e98c0ea043952953871bf0ea6d40076005614069a2fd7c2ecd3f5e1bd44b23ec74676b9bc99115cc0ef949855d689d0dd0000015bb0e5321b0000040300473045022100ed9e16c54948be03006a72f55130134980f85f7f0a9b68101700e1e2191d5413022069dccf66d74dbea91d7f4214f6da60793683f9e805941a69463e4fe551582cc1007600ee4bbdb775ce60bae142691fabe19e66a30f7e5fb072d88300c47b897aa8fdcb0000015bb0e534040000040300473045022013aa90205917714c97801332e6d366a2fca373cc9347525d008785fb58ccb8ef022100800960884ee1d6c649dc81a1d1d1f2f30a4adf4b36642fd377fa92886f6ad4b3007500bbd9dfbc1f8a71b593942397aa927b473857950aab52e81a909664368e1ed1850000015bb0e5321c00000403004630440220436a7ec846300247c2518e5f0fb44afde046e66a64f075ac1b4fc8209da7e06c0220612048bf6a1f1dbc11c119f957b7ad677557925de1dc63ee04a0b7ebd1877712"}]},{"length":1205,"serial_number":"04e1e7a4dc5cf2f36dc02b42b85d159f","signature":"2a864886f70d01010b","signature_key_size":2048,"issuer":[{"issuer_id":"550406","issuer_string":"US"},{"issuer_id":"55040a","issuer_string":"DigiCert Inc"},{"issuer_id":"55040b","issuer_string":"www.digicert.com"},{"issuer_id":"550403","issuer_string":"DigiCert High Assurance EV Root CA"}],"validity_not_before":"131022120000Z","validity_not_after":"281022120000Z","subject":[{"subject_id":"550406","subject_string":"US"},{"subject_id":"55040a","subject_string":"DigiCert Inc"},{"subject_id":"55040b","subject_string":"www.digicert.com"},{"subject_id":"550403","subject_string":"DigiCert SHA2 High Assurance Server CA"}],"subject_public_key_algorithm":"2a864886f70d010101","subject_public_key_size":2048,"extensions":[{"ext_id":"551d13","ext_data":"0101ff040830060101ff020100"},{"ext_id":"551d0f","ext_data":"0101ff040403020186"},{"ext_id":"551d25","ext_data":"0416301406082b0601050507030106082b06010505070302"},{"ext_id":"2b06010505070101","ext_data":"04283026302406082b060105050730018618687474703a2f2f6f6373702e64696769636572742e636f6d"},{"ext_id":"551d1f","ext_data":"044430423040a03ea03c863a687474703a2f2f63726c342e64696769636572742e636f6d2f4469676943657274486967684173737572616e63654556526f6f7443412e63726c"},{"ext_id":"551d20","ext_data":"0436303430320604551d2000302a302806082b06010505070201161c68747470733a2f2f7777772e64696769636572742e636f6d2f435053"},{"ext_id":"551d0e","ext_data":"041604145168ff90af0207753cccd9656462a212b859723b"},{"ext_id":"551d23","ext_data":"041830168014b13ec36903f8bf4701d498261a0802ef63642bc3"}]}],"srlt":[{"b":195,"dir":">","ipt":0,"tp":"22:1"},{"b":74,"dir":"<","ipt":2,"tp":"22:2"},{"b":3234,"dir":"<","ipt":0,"tp":"22:11"},{"b":70,"dir":">","ipt":3,"tp":"22:16"},{"b":1,"dir":">","ipt":0,"tp":"20:0"},{"b":40,"dir":">","ipt":0,"tp":"22:0"},{"b":76,"dir":"<","ipt":1,"tp":"23:0"},{"b":48,"dir":">","ipt":7,"tp":"23:0"},{"b":51,"dir":">","ipt":0,"tp":"23:0"},{"b":37,"dir":">","ipt":0,"tp":"23:0"},{"b":33,"dir":">","ipt":0,"tp":"23:0"},{"b":336,"dir":">","ipt":0,"tp":"23:0"},{"b":33,"dir":"<","ipt":0,"tp":"23:0"},{"b":37,"dir":"<","ipt":0,"tp":"23:0"},{"b":474,"dir":"<","ipt":31,"tp":"23:0"},{"b":33,"dir":"<","ipt":0,"tp":"23:0"},{"b":245,"dir":">","ipt":1,"tp":"23:0"},{"b":37,"dir":"<","ipt":1,"tp":"23:0"},{"b":222,"dir":"<","ipt":31,"tp":"23:0"}]}}
